cae/__init__.py
cae/py.typed
cae/examples/smoke.py
cae/sdk/__init__.py
cae/sdk/decorators.py
cae/sdk/exports.py
cae/sdk/http_api.py
cae/sdk/langchain_shim.py
cae/sdk/langchain_shim.pyi
cae/sdk/langgraph_shim.py
cae/sdk/langgraph_shim.pyi
cae/sdk/mcp.py
cae/sdk/registry.py
aiel_sdk-1.0.0.dist-info/METADATA
aiel_sdk-1.0.0.dist-info/WHEEL
aiel_sdk-1.0.0.dist-info/licenses/LICENSE
aiel_sdk-1.0.0.dist-info/RECORD
