Metadata-Version: 2.4
Name: aiel-sdk
Version: 1.0.0
Summary: AI Execution Layer SDK (contracts + registry + decorators)
Author-email: Aldenir Flauzino <aldenirsrv@gmail.com>
License: ```text
License-File: LICENSE
Requires-Python: >=3.10
Requires-Dist: typing-extensions>=4.8.0
